almax_graphics/__init__.py
almax_graphics/__main__.py
almax_graphics/managers/FrameManager.py
almax_graphics/managers/__init__.py
almax_graphics/tests/__init__.py
almax_graphics/tests/test_FrameManager.py
almax_graphics-2.0.0.dist-info/METADATA
almax_graphics-2.0.0.dist-info/WHEEL
almax_graphics-2.0.0.dist-info/top_level.txt
almax_graphics-2.0.0.dist-info/RECORD
